# ç¥ç§˜çš„Lambda

 

## æ¥è§¦èƒŒæ™¯ 

ç¬¬ä¸€æ¬¡æ¥è§¦lambdaè¡¨è¾¾å¼æ—¶ï¼Œæ„Ÿè§‰è¿™ä¸ªä¸œè¥¿æŒºç¥å¥‡çš„ï¼ˆé«˜é€¼æ ¼ï¼‰ï¼Œä¸€ä¸ªï¼ˆï¼‰åŠ ->å°±èƒ½ä¼ é€’ä¸€æ®µä»£ç ï¼Œå½“æ—¶å…¬å¸é¡¹ç›®ä¸­æ¥æ‰‹åŒäº‹çš„ä»£ç ï¼Œè‡ªå·±ä¹Ÿå¯¹java8çš„ç‰¹æ€§ä¸äº†è§£ï¼Œçœ‹çš„ä¹Ÿæ˜¯ä¸€å¤´é›¾æ°´ï¼Œä¹‹åå°±èµ¶å¿«çœ‹äº†ä¸‹ã€Šjava8å®æˆ˜ã€‹è¿™æœ¬ä¹¦ï¼Œå†³å®šå†™ä¸€ä¸ªjava8ç‰¹æ€§ç³»åˆ—çš„åšå®¢ï¼Œæ—¢åŠ æ·±è‡ªå·±çš„å°è±¡ï¼Œè¿˜èƒ½è·Ÿå¤§å®¶åˆ†äº«ä¸€ä¸‹ï¼Œå¸Œæœ›å¤§å®¶å¤šå¤šæŒ‡æ•™ğŸ˜„ã€‚ 

### *ä»€ä¹ˆæ˜¯Lambdaï¼Ÿ*

Lambdaæ˜¯ä¸€ä¸ªåŒ¿åå‡½æ•°ï¼Œæˆ‘ä»¬å¯ä»¥æŠŠLambdaè¡¨è¾¾å¼ç†è§£ä¸ºæ˜¯ä¸€æ®µå¯ä»¥ä¼ é€’çš„ä»£ç (å°†ä»£ç åƒå‚æ•°ä¸€æ ·è¿›è¡Œä¼ é€’ï¼Œç§°ä¸ºè¡Œä¸ºå‚æ•°åŒ–)ã€‚Lambdaå…è®¸æŠŠå‡½æ•°ä½œä¸ºä¸€ä¸ªæ–¹æ³•çš„å‚æ•°ï¼ˆå‡½æ•°ä½œä¸ºå‚æ•°ä¼ é€’è¿›æ–¹æ³•ä¸­ï¼‰ï¼Œè¦åšåˆ°è¿™ä¸€ç‚¹å°±éœ€è¦äº†è§£ï¼Œä»€ä¹ˆæ˜¯å‡½æ•°å¼æ¥å£ï¼Œè¿™é‡Œå…ˆä¸åšä»‹ç»ï¼Œç­‰ä¸‹ä¸€ç¯‡åœ¨è®²è§£ã€‚ 

é¦–å…ˆå…ˆçœ‹ä¸€ä¸‹lambdaé•¿ä»€ä¹ˆæ ·ï¼Ÿ æ­£å¸¸å†™æ³•ï¼š 

```java
new Thread(new Runnable() { 
  @Override 
  public void run() { 
     System.out.println("hello lambda"); 
  } 
}).start(); 
```

lambdaå†™æ³•ï¼š 

```java
new Thread( 
  () -> System.out.println("hello lambda") 
).start(); 
```

æ€ä¹ˆæ ·ï¼Ÿæ˜¯ä¸æ˜¯æ„Ÿè§‰å¾ˆç®€æ´ï¼Œæ²¡é”™ï¼Œè¿™å°±æ˜¯lambdaçš„é­…åŠ›ï¼Œä»–å¯ä»¥è®©ä½ å†™å‡ºæ¥çš„ä»£ç æ›´ç®€å•ã€æ›´çµæ´»ã€‚ 

### *Lambdaæ€ä¹ˆå†™ï¼Ÿ* 

å¤§å®¶çœ‹ä¸€äº›ä¸Šé¢çš„è¿™ä¸ªå›¾ï¼Œè¿™å°±æ˜¯lambdaçš„è¯­æ³•ï¼Œä¸€ä¸ªlambdaåˆ†ä¸ºä¸‰éƒ¨åˆ†ï¼šå‚æ•°åˆ—è¡¨ã€æ“ä½œç¬¦ã€lambdaä½“ã€‚ä»¥ä¸‹æ˜¯lambdaè¡¨è¾¾å¼çš„é‡è¦ç‰¹å¾ï¼š 

- å¯é€‰ç±»å‹å£°æ˜ï¼š ä¸éœ€è¦å£°æ˜å‚æ•°ç±»å‹ï¼Œç¼–è¯‘å™¨å¯ä»¥ç»Ÿä¸€è¯†åˆ«å‚æ•°å€¼ã€‚ä¹Ÿå°±è¯´(s) -> System.out.println(s)å’Œ (String s) -> System.out.println(s)æ˜¯ä¸€æ ·çš„ç¼–è¯‘å™¨ä¼šè¿›è¡Œç±»å‹æ¨æ–­æ‰€ä»¥ä¸éœ€è¦æ·»åŠ å‚æ•°ç±»å‹ã€‚ 
- å¯é€‰çš„å‚æ•°åœ†æ‹¬å·ï¼š ä¸€ä¸ªå‚æ•°æ— éœ€å®šä¹‰åœ†æ‹¬å·ï¼Œä½†å¤šä¸ªå‚æ•°éœ€è¦å®šä¹‰åœ†æ‹¬å·ã€‚ä¾‹å¦‚ï¼š 

> 1. s -> System.out.println(s) ä¸€ä¸ªå‚æ•°ä¸éœ€è¦æ·»åŠ åœ†æ‹¬å·ã€‚ 
> 2. (x, y) -> Integer.compare(y, x) ä¸¤ä¸ªå‚æ•°æ·»åŠ äº†åœ†æ‹¬å·ï¼Œå¦åˆ™ç¼–è¯‘å™¨æŠ¥é”™ã€‚ 
>

- å¯é€‰çš„å¤§æ‹¬å·ï¼š å¦‚æœä¸»ä½“åŒ…å«äº†ä¸€ä¸ªè¯­å¥ï¼Œå°±ä¸éœ€è¦ä½¿ç”¨å¤§æ‹¬å·ã€‚ 

> 1. s -> System.out.println(s) , ä¸éœ€è¦å¤§æ‹¬å·. 
> 2. (s) -> { if (s.equals("s")){ System.out.println(s); } }; éœ€è¦å¤§æ‹¬å· 
>

- å¯é€‰çš„è¿”å›å…³é”®å­—ï¼š å¦‚æœä¸»ä½“åªæœ‰ä¸€ä¸ªè¡¨è¾¾å¼è¿”å›å€¼åˆ™ç¼–è¯‘å™¨ä¼šè‡ªåŠ¨è¿”å›å€¼ï¼Œå¤§æ‹¬å·éœ€è¦æŒ‡å®šæ˜è¡¨è¾¾å¼è¿”å›äº†ä¸€ä¸ªæ•°å€¼ã€‚ 

Lambdaä½“ä¸åŠ { }å°±ä¸ç”¨å†™return: 

```java
Comparator<Integer> com = (x, y) -> Integer.compare(y, x); 
//Lambdaä½“åŠ ä¸Š{ }å°±éœ€è¦æ·»åŠ return: 
Comparator<Integer> com = (x, y) -> {
  int compare = Integer.compare(y, x); 
  return compare; 

}; 
```

### *ç±»å‹æ¨æ–­* 

ä¸Šé¢æˆ‘ä»¬çœ‹åˆ°äº†ä¸€ä¸ªlambdaè¡¨è¾¾å¼åº”è¯¥æ€ä¹ˆå†™ï¼Œä½†lambdaä¸­æœ‰ä¸€ä¸ªé‡è¦ç‰¹å¾æ˜¯å¯é€‰å‚æ•°ç±»å‹å£°æ˜ï¼Œå°±æ˜¯è¯´ä¸ç”¨å†™å‚æ•°çš„ç±»å‹ï¼Œé‚£ä¹ˆä¸ºä»€ä¹ˆä¸ç”¨å†™å‘¢ï¼Ÿå®ƒæ˜¯æ€ä¹ˆçŸ¥é“çš„å‚æ•°ç±»å‹å‘¢ï¼Ÿè¿™å°±æ¶‰åŠåˆ°ç±»å‹æ¨æ–­äº†ã€‚ 

**java8çš„æ³›å‹ç±»å‹æ¨æ–­æ”¹è¿›ï¼š** 

- æ”¯æŒé€šè¿‡æ–¹æ³•ä¸Šä¸‹æ–‡æ¨æ–­æ³›å‹ç›®æ ‡ç±»å‹ 
- æ”¯æŒåœ¨æ–¹æ³•è°ƒç”¨é“¾è·¯ä¸­ï¼Œæ³›å‹ç±»å‹æ¨æ–­ä¼ é€’åˆ°æœ€åä¸€ä¸ªæ–¹æ³• 

```java
List<Person> ps = ... 

Stream<String> names = ps.stream().map(p -> p.getName()); 
```

åœ¨ä¸Šé¢çš„ä»£ç ä¸­ï¼Œpsçš„ç±»å‹æ˜¯List<Person>ï¼Œæ‰€ä»¥ps.stream()çš„è¿”å›ç±»å‹æ˜¯Stream<Person>ã€‚map()æ–¹æ³•æ¥æ”¶ä¸€ä¸ªç±»å‹ä¸ºFunction<T, R>çš„å‡½æ•°å¼æ¥å£ï¼Œè¿™é‡ŒTçš„ç±»å‹å³æ˜¯Streamå…ƒç´ çš„ç±»å‹ï¼Œä¹Ÿå°±æ˜¯Personï¼Œè€ŒRçš„ç±»å‹æœªçŸ¥ã€‚ç”±äºåœ¨é‡è½½è§£æä¹‹ålambdaè¡¨è¾¾å¼çš„ç›®æ ‡ç±»å‹ä»ç„¶æœªçŸ¥ï¼Œæˆ‘ä»¬å°±éœ€è¦æ¨å¯¼Rçš„ç±»å‹ï¼šé€šè¿‡å¯¹lambdaè¡¨è¾¾å¼lambdaè¿›è¡Œç±»å‹æ£€æŸ¥ï¼Œæˆ‘ä»¬å‘ç°lambdaä½“è¿”å›Stringï¼Œå› æ­¤Rçš„ç±»å‹æ˜¯Stringï¼Œå› è€Œmap()è¿”å›Stream<String>ã€‚ç»å¤§å¤šæ•°æƒ…å†µä¸‹ç¼–è¯‘å™¨éƒ½èƒ½è§£æå‡ºæ­£ç¡®çš„ç±»å‹ï¼Œä½†å¦‚æœç¢°åˆ°æ— æ³•è§£æçš„æƒ…å†µï¼Œæˆ‘ä»¬åˆ™éœ€è¦ï¼š 

- ä½¿ç”¨æ˜¾å¼lambdaè¡¨è¾¾å¼ï¼ˆä¸ºå‚æ•°pæä¾›æ˜¾å¼ç±»å‹ï¼‰ä»¥æä¾›é¢å¤–çš„ç±»å‹ä¿¡æ¯ 
- æŠŠlambdaè¡¨è¾¾å¼è½¬å‹ä¸ºFunction<Person, String> 
- ä¸ºæ³›å‹å‚æ•°Ræä¾›ä¸€ä¸ªå®é™…ç±»å‹ã€‚ï¼ˆ <String>map(p -> p.getName())ï¼‰ 

### *æ–¹æ³•å¼•ç”¨* 

æ–¹æ³•å¼•ç”¨æ˜¯ç”¨æ¥ç›´æ¥è®¿é—®ç±»æˆ–è€…å®ä¾‹å·²ç»å­˜åœ¨çš„æ–¹æ³•æˆ–æ„é€ æ–¹æ³•ï¼Œæä¾›äº†ä¸€ç§å¼•ç”¨è€Œä¸æ‰§è¡Œæ–¹æ³•çš„æ–¹å¼ã€‚æ˜¯ä¸€ç§æ›´ç®€æ´æ›´æ˜“æ‡‚çš„Lambdaè¡¨è¾¾å¼ï¼Œå½“Lambdaè¡¨è¾¾å¼ä¸­åªæ˜¯æ‰§è¡Œä¸€ä¸ªæ–¹æ³•è°ƒç”¨æ—¶ï¼Œç›´æ¥ä½¿ç”¨æ–¹æ³•å¼•ç”¨çš„å½¢å¼å¯è¯»æ€§æ›´é«˜ä¸€äº›ã€‚ æ–¹æ³•å¼•ç”¨ä½¿ç”¨ â€œ :: â€ æ“ä½œç¬¦æ¥è¡¨ç¤ºï¼Œå·¦è¾¹æ˜¯ç±»åæˆ–å®ä¾‹åï¼Œå³è¾¹æ˜¯æ–¹æ³•åã€‚ ï¼ˆæ³¨æ„ï¼šæ–¹æ³•å¼•ç”¨::å³è¾¹çš„æ–¹æ³•åæ˜¯ä¸éœ€è¦åŠ ï¼ˆï¼‰çš„ï¼Œä¾‹ï¼šUser::getNameï¼‰ 

**æ–¹æ³•å¼•ç”¨çš„å‡ ç§å½¢å¼ï¼š** 

- ç±» :: é™æ€æ–¹æ³• 
- ç±» :: å®ä¾‹æ–¹æ³• 
- å¯¹è±¡ :: å®ä¾‹æ–¹æ³• 

ä¾‹å¦‚ï¼š 

 ``` Consumer<String> consumer = (s) -> System.out.println(s); ```

ç­‰åŒäºï¼š 

 ``` Consumer<String> consumer = System.out::println; ```

ä¾‹å¦‚ï¼š 

  ```Function<String, Integer> stringToInteger = (String s) -> Integer.parseInt(s); ```

ç­‰åŒäºï¼š 

 ``` Function<String, Integer> stringToInteger = Integer::parseInt; ```

ä¾‹å¦‚ï¼š 

```  BiPredicate<List<String>, String> contains = (list, element) ->list.contains(element); ```

ç­‰åŒäºï¼š 

 ``` BiPredicate<List<String>, String> contains = List::contains; ```

**æ³¨æ„:** 

- Lambdaä½“ä¸­è°ƒç”¨æ–¹æ³•çš„å‚æ•°åˆ—è¡¨ä¸è¿”å›å€¼ç±»å‹ï¼Œè¦ä¸å‡½æ•°å¼æ¥å£ä¸­æŠ½è±¡æ–¹æ³•çš„å‡½æ•°åˆ—è¡¨å’Œè¿”å›å€¼ç±»å‹ä¿å­˜ä¸€è‡´ 
- è‹¥Lambdaå‚æ•°åˆ—è¡¨ä¸­çš„ç¬¬ä¸€ä¸ªå‚æ•°æ˜¯å®ä¾‹æ–¹æ³•çš„è°ƒç”¨è€…ï¼Œè€Œç¬¬äºŒä¸ªå‚æ•°æ˜¯å®ä¾‹æ–¹æ³•çš„å‚æ•°æ—¶ï¼Œå¯ä»¥ä½¿ç”¨ClassName::method 

 

### *æ„é€ å™¨å¼•ç”¨* 

è¯­æ³•æ ¼å¼ï¼šç±»å::new 

ä¾‹å¦‚ï¼š 

```  Supplier<User> supplier = ()->new User(); ```

 

ç­‰åŒäºï¼š 

```  Supplier<User> supplier = User::new; ```

**æ³¨æ„:** éœ€è¦è°ƒç”¨çš„æ„é€ å™¨æ–¹æ³•ä¸å‡½æ•°å¼æ¥å£ä¸­æŠ½è±¡æ–¹æ³•çš„å‚æ•°åˆ—è¡¨ä¿æŒä¸€è‡´ã€‚ 

 

### *Lambdaæ˜¯æ€ä¹ˆå®ç°çš„ï¼Ÿ* 

ç ”ç©¶äº†åŠå¤©Lambdaæ€ä¹ˆå†™ï¼Œå¯æ˜¯å®ƒçš„åŸç†æ˜¯ä»€ä¹ˆï¼Ÿæˆ‘ä»¬ç®€å•çœ‹ä¸ªä¾‹å­ï¼Œçœ‹çœ‹çœŸç›¸åˆ°åº•æ˜¯ä»€ä¹ˆï¼š 

```java
public class StreamTest { 

  public static void main(String[] args) { 
      printString("hello lambda", (String s) -> System.out.println(s)); 
  } 

  public static void printString(String s, Print<String> print) { 
	print.print(s); 
  } 
} 

@FunctionalInterface 
interface Print<T> { 
  public void print(T t); 
} 
```

ä¸Šé¢çš„ä»£ç è‡ªå®šä¹‰äº†ä¸€ä¸ªå‡½æ•°å¼æ¥å£ï¼Œå®šä¹‰ä¸€ä¸ªé™æ€æ–¹æ³•ç„¶åç”¨è¿™ä¸ªå‡½æ•°å¼æ¥å£æ¥æ¥æ”¶å‚æ•°ã€‚ç¼–å†™å®Œè¿™ä¸ªç±»ä»¥åï¼Œæˆ‘ä»¬åˆ°ç»ˆç«¯ç•Œé¢javacè¿›è¡Œç¼–è¯‘ï¼Œç„¶åç”¨javapï¼ˆjavapæ˜¯jdkè‡ªå¸¦çš„åè§£æå·¥å…·ã€‚å®ƒçš„ä½œç”¨å°±æ˜¯æ ¹æ®classå­—èŠ‚ç æ–‡ä»¶ï¼Œåè§£æå‡ºå½“å‰ç±»å¯¹åº”çš„codeåŒºï¼ˆæ±‡ç¼–æŒ‡ä»¤ï¼‰ã€æœ¬åœ°å˜é‡è¡¨ã€å¼‚å¸¸è¡¨å’Œä»£ç è¡Œåç§»é‡æ˜ å°„è¡¨ã€å¸¸é‡æ± ç­‰ç­‰ä¿¡æ¯ã€‚ï¼‰è¿›è¡Œè§£æï¼Œå¦‚ä¸‹å›¾ï¼š 

- æ‰§è¡Œjavap -p å‘½ä»¤ ( -p -private æ˜¾ç¤ºæ‰€æœ‰ç±»å’Œæˆå‘˜) 

çœ‹ä¸Šå›¾å‘ç°åœ¨ç¼–è¯‘Lambdaè¡¨è¾¾å¼ç”Ÿæˆäº†ä¸€ä¸ªlambda$main$0é™æ€æ–¹æ³•ï¼Œè¿™ä¸ªé™æ€æ–¹æ³•å®ç°äº†Lambdaè¡¨è¾¾å¼çš„é€»è¾‘ï¼Œç°åœ¨æˆ‘ä»¬çŸ¥é“åŸæ¥Lambdaè¡¨è¾¾å¼è¢«ç¼–è¯‘æˆäº†ä¸€ä¸ªé™æ€æ–¹æ³•ï¼Œé‚£ä¹ˆè¿™ä¸ªé™æ€æ–¹å¼æ˜¯æ€ä¹ˆè°ƒç”¨çš„å‘¢ï¼Ÿæˆ‘ä»¬ç»§ç»­è¿›è¡Œ 

- æ‰§è¡Œjavap -v -p å‘½ä»¤ ( -v -verbose è¾“å‡ºé™„åŠ ä¿¡æ¯) 

```java
public com.lxs.stream.StreamTest(); 
  descriptor: ()V 
  flags: ACC_PUBLIC 
  Code: 
â€‹    stack=1, locals=1, args_size=1 
â€‹      0: aload_0 
â€‹      1: invokespecial #1 // Method java/lang/Object."<init>":()V 
â€‹      4: return 
  LineNumberTable: 
â€‹    line 7: 0 
  public static void main(java.lang.String[]); 
â€‹    descriptor: ([Ljava/lang/String;)V 
â€‹    flags: ACC_PUBLIC, ACC_STATIC 
â€‹    Code: 
â€‹      stack=2, locals=1, args_size=1 
â€‹        0: ldc #2 // String hello lambda 
â€‹        2: invokedynamic #3, 0 // InvokeDynamic #0:print:()Lcom/lxs/stream/Print; 
â€‹        7: invokestatic #4 // Method printString:(Ljava/lang/String;Lcom/lxs/stream/Print;)V 
â€‹        10: return 
â€‹    LineNumberTable: 
â€‹      line 10: 0 
â€‹      line 12: 10 

  public static void printString(java.lang.String, com.lxs.stream.Print<java.lang.String>); 
â€‹    descriptor: (Ljava/lang/String;Lcom/lxs/stream/Print;)V 
â€‹      flags: ACC_PUBLIC, ACC_STATIC 
â€‹    Code: 
â€‹      stack=2, locals=2, args_size=2 
â€‹        0: aload_1 
â€‹        1: aload_0 
â€‹        2: invokeinterface #5, 2 // InterfaceMethod com/lxs/stream/Print.print:(Ljava/lang/Object;)V 
â€‹        7: return 
â€‹    LineNumberTable: 
â€‹      line 15: 0 
â€‹      line 16: 7 
â€‹    Signature: #19 // (Ljava/lang/String;Lcom/lxs/stream/Print<Ljava/lang/String;>;)V 
 
  private static void lambda$main$0(java.lang.String); 
â€‹    descriptor: (Ljava/lang/String;)V 
â€‹    flags: ACC_PRIVATE, ACC_STATIC, ACC_SYNTHETIC 
â€‹    Code: 
â€‹      stack=2, locals=1, args_size=1 
â€‹        0: getstatic #6 // Field java/lang/System.out:Ljava/io/PrintStream; 
â€‹        3: aload_0 
â€‹        4: invokevirtual #7 // Method java/io/PrintStream.println:(Ljava/lang/String;)V 
â€‹        7: return 
â€‹    LineNumberTable: 
â€‹      line 10: 0 
} 
 
SourceFile: "StreamTest.java" 
InnerClasses: 
â€‹    public static final #58= #57 of #61; //Lookup=class java/lang/invoke/MethodHandles$Lookup of class java/lang/invoke/MethodHandles 
 
BootstrapMethods: 
  0: #27 invokestatic java/lang/invoke/LambdaMetafactory.metafactory:(Ljava/lang/invoke/MethodHandles$Lookup;Ljava/lang/String;Ljava/lang/invoke/MethodType;Ljava/lang/invoke/MethodType;Ljava/lang/invoke/MethodHandle;Ljava/lang/invoke/MethodType;)Ljava/lang/invoke/CallSite; 
 
  Method arguments: 
â€‹    \#28 (Ljava/lang/Object;)V 
â€‹    \#29 invokestatic com/lxs/stream/StreamTest.lambda$main$0:(Ljava/lang/String;)V 
â€‹    \#30 (Ljava/lang/String;)V 
//è¿™é‡Œåªè´´å‡ºäº†ä¸€éƒ¨åˆ†çš„å­—èŠ‚ç ç»“æ„ï¼Œç”±äºå¸¸é‡æ± å®šä¹‰å¤ªé•¿äº†ï¼Œå°±æ²¡æœ‰ç²˜è´´ã€‚ 
InnerClasses: 
   public static final #58= #57 of #61; //Lookup=class java/lang/invoke/MethodHandles$Lookup of class java/lang/invoke/MethodHandles 
BootstrapMethods: 
 0: #27 invokestatic java/lang/invoke/LambdaMetafactory.metafactory:(Ljava/lang/invoke/MethodHandles$Lookup;Ljava/lang/String;Ljava/lang/invoke/MethodType;Ljava/lang/invoke/MethodType;Ljava/lang/invoke/MethodHandle;Ljava/lang/invoke/MethodType;)Ljava/lang/invoke/CallSite; 
  Method arguments: 
   \#28 (Ljava/lang/Object;)V 
   \#29 invokestatic com/lxs/stream/StreamTest.lambda$main
    $0:(Ljava/lang/String;)V 
   \#30 (Ljava/lang/String;)V 
```

é€šè¿‡è¿™æ®µå­—èŠ‚ç ç»“æ„å‘ç°æ˜¯è¦ç”Ÿæˆä¸€ä¸ªå†…éƒ¨ç±»ï¼Œä½¿ç”¨invokestaticè°ƒç”¨äº†ä¸€ä¸ªLambdaMetafactory.metafactoryæ–¹æ³•ï¼Œå¹¶æŠŠlambda$main$0ä½œä¸ºå‚æ•°ä¼ äº†è¿›å»ï¼Œæˆ‘ä»¬æ¥çœ‹metafactory çš„æ–¹æ³•é‡Œçš„å®ç°ä»£ç ï¼š 

```java
  public static CallSite metafactory(MethodHandles.Lookup caller, 
                    String invokedName, 
                    MethodType invokedType, 
                    MethodType samMethodType, 
                    MethodHandle implMethod, 
                    MethodType instantiatedMethodType) 
      throws LambdaConversionException { 
    AbstractValidatingLambdaMetafactory mf; 
    mf = new InnerClassLambdaMetafactory(caller, invokedType, 
                       invokedName, samMethodType, 
                       implMethod, instantiatedMethodType, 
                       false, EMPTY_CLASS_ARRAY, EMPTY_MT_ARRAY); 
    mf.validateMetafactoryArgs(); 
    return mf.buildCallSite(); 
  } 
```

åœ¨buildCallSiteçš„å‡½æ•°ä¸­,æ˜¯å‡½æ•°spinInnerClass æ„å»ºäº†è¿™ä¸ªå†…éƒ¨ç±»ã€‚ä¹Ÿå°±æ˜¯ç”Ÿæˆäº†ä¸€ä¸ªStreamTest$$Lambda$1.classè¿™æ ·çš„å†…éƒ¨ç±»,è¿™ä¸ªç±»æ˜¯åœ¨è¿è¡Œçš„æ—¶å€™æ„å»ºçš„ï¼Œå¹¶ä¸ä¼šä¿å­˜åœ¨ç£ç›˜ä¸­ã€‚ 

```java
  @Override 
  CallSite buildCallSite() throws LambdaConversionException { 
    final Class<?> innerClass = spinInnerClass(); 
    ä»¥ä¸‹çœç•¥ã€‚ã€‚ã€‚ 
  } 
```

å¦‚æœæƒ³çœ‹åˆ°è¿™ä¸ªæ„å»ºçš„ç±»ï¼Œå¯ä»¥é€šè¿‡è®¾ç½®ç¯å¢ƒå‚æ•° System.setProperty("jdk.internal.lambda.dumpProxyClasses", " . "); ä¼šåœ¨ä½ æŒ‡å®šçš„è·¯å¾„ . å½“å‰è¿è¡Œè·¯å¾„ä¸Šç”Ÿæˆè¿™ä¸ªå†…éƒ¨ç±»ã€‚æˆ‘ä»¬çœ‹ä¸‹ä¸€ä¸‹ç”Ÿæˆçš„ç±»é•¿ä»€ä¹ˆæ · 

ä»å›¾ä¸­å¯ä»¥çœ‹å‡ºåŠ¨æ€ç”Ÿæˆçš„å†…éƒ¨ç±»å®ç°äº†æˆ‘è‡ªå®šä¹‰çš„å‡½æ•°å¼æ¥å£ï¼Œå¹¶ä¸”é‡å†™äº†å‡½æ•°å¼æ¥å£ä¸­çš„æ–¹æ³•ã€‚ 

æˆ‘ä»¬åœ¨javap -v -p StreamTest$$Lambda$1.classçœ‹ä¸‹ï¼š 

```java
{ 
 private com.lxs.stream.StreamTest$$Lambda$1(); 
  descriptor: ()V 
  flags: ACC_PRIVATE 
  Code: 
   stack=1, locals=1, args_size=1 
     0: aload_0 
     1: invokespecial #10         // Method java/lang/Object."<init>":()V 
     4: return 
 
 public void print(java.lang.Object); 
  descriptor: (Ljava/lang/Object;)V 
  flags: ACC_PUBLIC 
  Code: 
   stack=1, locals=2, args_size=2 
     0: aload_1 
     1: checkcast   #15         // class java/lang/String 
     4: invokestatic #21         // Method com/lxs/stream/StreamTest.lambda$main$0:(Ljava/lang/String;)V 
     7: return 
  RuntimeVisibleAnnotations: 
   0: #13() 
} 
```

å‘ç°åœ¨é‡å†™çš„parintæ–¹æ³•ä¸­ä½¿ç”¨invokestaticæŒ‡ä»¤è°ƒç”¨äº†lambda$main$0æ–¹æ³•ã€‚ 

**æ€»ç»“ï¼š** è¿™æ ·å®ç°äº†Lambdaè¡¨è¾¾å¼ï¼Œä½¿ç”¨invokedynamicæŒ‡ä»¤ï¼Œè¿è¡Œæ—¶è°ƒç”¨LambdaMetafactory.metafactoryåŠ¨æ€çš„ç”Ÿæˆå†…éƒ¨ç±»ï¼Œå®ç°äº†å‡½æ•°å¼æ¥å£ï¼Œå¹¶åœ¨é‡å†™å‡½æ•°å¼æ¥å£ä¸­çš„æ–¹æ³•ï¼Œåœ¨æ–¹æ³•å†…è°ƒç”¨lambda$main$0ï¼Œå†…éƒ¨ç±»é‡Œçš„è°ƒç”¨æ–¹æ³•å—å¹¶ä¸æ˜¯åŠ¨æ€ç”Ÿæˆçš„ï¼Œåªæ˜¯åœ¨åŸclassé‡Œå·²ç»ç¼–è¯‘ç”Ÿæˆäº†ä¸€ä¸ªé™æ€çš„æ–¹æ³•ï¼Œå†…éƒ¨ç±»åªéœ€è¦è°ƒç”¨è¯¥é™æ€æ–¹æ³•ã€‚ 